pyrcdevs/__init__.py
pyrcdevs/constants.py
pyrcdevs/manager/Manager.py
pyrcdevs/manager/OpenOTPManager.py
pyrcdevs/manager/PwResetManager.py
pyrcdevs/manager/SelfRegManager.py
pyrcdevs/manager/SpanKeyManager.py
pyrcdevs/manager/WebADMManager.py
pyrcdevs/manager/__init__.py
pyrcdevs/soap/OpenOTPSoap.py
pyrcdevs/soap/SMSHubSoap.py
pyrcdevs/soap/SOAP.py
pyrcdevs/soap/SpanKeySoap.py
pyrcdevs/soap/__init__.py
pyrcdevs-2.0.2.dist-info/LICENSE
pyrcdevs-2.0.2.dist-info/METADATA
pyrcdevs-2.0.2.dist-info/WHEEL
pyrcdevs-2.0.2.dist-info/RECORD
