Metadata-Version: 2.3
Name: pyrcdevs
Version: 2.0.2
Summary: Python library for using the RCDevs API (Manager and SOAP APIs)
Author: RCDevs Security
Author-email: devel@rcdevs.com
Maintainer: Benoît Jager
Requires-Python: >=3.10,<4.0
Classifier: Programming Language :: Python :: 3
Classifier: Programming Language :: Python :: 3.10
Classifier: Programming Language :: Python :: 3.11
Classifier: Programming Language :: Python :: 3.12
Classifier: Programming Language :: Python :: 3.13
Requires-Dist: aiohttp (>=3.11.16,<4.0.0)
Requires-Dist: xmltodict (>=0.14.2,<0.15.0)
Project-URL: Documentation, https://docs.rcdevs.com/
Project-URL: Homepage, https://www.rcdevs.com/
